#ifndef OPCODES_H
#define OPCODES_H

typedef enum opcode_kind_t {
	OPC_NOP             = 0x00,
	OPC_ACONST_NULL     = 0x01,
	OPC_ICONST_M1       = 0x02,
	OPC_ICONST_0        = 0x03,
	OPC_ICONST_1        = 0x04,
	OPC_ICONST_2        = 0x05,
	OPC_ICONST_3        = 0x06,
	OPC_ICONST_4        = 0x07,
	OPC_ICONST_5        = 0x08,
	OPC_LCONST_0        = 0x09,
	OPC_LCONST_1        = 0x0A,
	OPC_FCONST_0        = 0x0B,
	OPC_FCONST_1        = 0x0C,
	OPC_FCONST_2        = 0x0D,
	OPC_DCONST_0        = 0x0E,
	OPC_DCONST_1        = 0x0F,
	OPC_BIPUSH          = 0x10,
	OPC_SIPUSH          = 0x11,
	OPC_LDC             = 0x12,
	OPC_LDC_W           = 0x13,
	OPC_LDC2_W          = 0x14,
	OPC_ILOAD           = 0x15,
	OPC_LLOAD           = 0x16,
	OPC_FLOAD           = 0x17,
	OPC_DLOAD           = 0x18,
	OPC_ALOAD           = 0x19,
	OPC_ILOAD_0         = 0x1A,
	OPC_ILOAD_1         = 0x1B,
	OPC_ILOAD_2         = 0x1C,
	OPC_ILOAD_3         = 0x1D,
	OPC_LLOAD_0         = 0x1E,
	OPC_LLOAD_1         = 0x1F,
	OPC_LLOAD_2         = 0x20,
	OPC_LLOAD_3         = 0x21,
	OPC_FLOAD_0         = 0x22,
	OPC_FLOAD_1         = 0x23,
	OPC_FLOAD_2         = 0x24,
	OPC_FLOAD_3         = 0x25,
	OPC_DLOAD_0         = 0x26,
	OPC_DLOAD_1         = 0x27,
	OPC_DLOAD_2         = 0x28,
	OPC_DLOAD_3         = 0x29,
	OPC_ALOAD_0         = 0x2A,
	OPC_ALOAD_1         = 0x2B,
	OPC_ALOAD_2         = 0x2C,
	OPC_ALOAD_3         = 0x2D,
	OPC_IALOAD          = 0x2E,
	OPC_LALOAD          = 0x2F,
	OPC_FALOAD          = 0x30,
	OPC_DALOAD          = 0x31,
	OPC_AALOAD          = 0x32,
	OPC_BALOAD          = 0x33,
	OPC_CALOAD          = 0x34,
	OPC_SALOAD          = 0x35,
	OPC_ISTORE          = 0x36,
	OPC_LSTORE          = 0x37,
	OPC_FSTORE          = 0x38,
	OPC_DSTORE          = 0x39,
	OPC_ASTORE          = 0x3A,
	OPC_ISTORE_0        = 0x3B,
	OPC_ISTORE_1        = 0x3C,
	OPC_ISTORE_2        = 0x3D,
	OPC_ISTORE_3        = 0x3E,
	OPC_LSTORE_0        = 0x3F,
	OPC_LSTORE_1        = 0x40,
	OPC_LSTORE_2        = 0x41,
	OPC_LSTORE_3        = 0x42,
	OPC_FSTORE_0        = 0x43,
	OPC_FSTORE_1        = 0x44,
	OPC_FSTORE_2        = 0x45,
	OPC_FSTORE_3        = 0x46,
	OPC_DSTORE_0        = 0x47,
	OPC_DSTORE_1        = 0x48,
	OPC_DSTORE_2        = 0x49,
	OPC_DSTORE_3        = 0x4A,
	OPC_ASTORE_0        = 0x4B,
	OPC_ASTORE_1        = 0x4C,
	OPC_ASTORE_2        = 0x4D,
	OPC_ASTORE_3        = 0x4E,
	OPC_IASTORE         = 0x4F,
	OPC_LASTORE         = 0x50,
	OPC_FASTORE         = 0x51,
	OPC_DASTORE         = 0x52,
	OPC_AASTORE         = 0x53,
	OPC_BASTORE         = 0x54,
	OPC_CASTORE         = 0x55,
	OPC_SASTORE         = 0x56,
	OPC_POP             = 0x57,
	OPC_POP2            = 0x58,
	OPC_DUP             = 0x59,
	OPC_DUP_X1          = 0x5A,
	OPC_DUP_X2          = 0x5B,
	OPC_DUP2            = 0x5C,
	OPC_DUP2_X1         = 0x5D,
	OPC_DUP2_X2         = 0x5E,
	OPC_SWAP            = 0x5F,
	OPC_IADD            = 0x60,
	OPC_LADD            = 0x61,
	OPC_FADD            = 0x62,
	OPC_DADD            = 0x63,
	OPC_ISUB            = 0x64,
	OPC_LSUB            = 0x65,
	OPC_FSUB            = 0x66,
	OPC_DSUB            = 0x67,
	OPC_IMUL            = 0x68,
	OPC_LMUL            = 0x69,
	OPC_FMUL            = 0x6A,
	OPC_DMUL            = 0x6B,
	OPC_IDIV            = 0x6C,
	OPC_LDIV            = 0x6D,
	OPC_FDIV            = 0x6E,
	OPC_DDIV            = 0x6F,
	OPC_IREM            = 0x70,
	OPC_LREM            = 0x71,
	OPC_FREM            = 0x72,
	OPC_DREM            = 0x73,
	OPC_INEG            = 0x74,
	OPC_LNEG            = 0x75,
	OPC_FNEG            = 0x76,
	OPC_DNEG            = 0x77,
	OPC_ISHL            = 0x78,
	OPC_LSHL            = 0x79,
	OPC_ISHR            = 0x7A,
	OPC_LSHR            = 0x7B,
	OPC_IUSHR           = 0x7C,
	OPC_LUSHR           = 0x7D,
	OPC_IAND            = 0x7E,
	OPC_LAND            = 0x7F,
	OPC_IOR             = 0x80,
	OPC_LOR             = 0x81,
	OPC_IXOR            = 0x82,
	OPC_LXOR            = 0x83,
	OPC_IINC            = 0x84,
	OPC_I2L             = 0x85,
	OPC_I2F             = 0x86,
	OPC_I2D             = 0x87,
	OPC_L2I             = 0x88,
	OPC_L2F             = 0x89,
	OPC_L2D             = 0x8a,
	OPC_F2I             = 0x8b,
	OPC_F2L             = 0x8c,
	OPC_F2D             = 0x8d,
	OPC_D2I             = 0x8e,
	OPC_D2L             = 0x8f,
	OPC_D2F             = 0x90,
	OPC_I2B             = 0x91,
	OPC_I2C             = 0x92,
	OPC_I2S             = 0x93,
	OPC_LCMP            = 0x94,
	OPC_FCMPL           = 0x95,
	OPC_FCMPG           = 0x96,
	OPC_DCMPL           = 0x97,
	OPC_DCMPG           = 0x98,
	OPC_IFEQ            = 0x99,
	OPC_IFNE            = 0x9A,
	OPC_IFLT            = 0x9B,
	OPC_IFGE            = 0x9C,
	OPC_IFGT            = 0x9D,
	OPC_IFLE            = 0x9E,
	OPC_ICMPEQ          = 0x9F,
	OPC_ICMPNE          = 0xA0,
	OPC_ICMPLT          = 0xA1,
	OPC_ICMPGE          = 0xA2,
	OPC_ICMPGT          = 0xA3,
	OPC_ICMPLE          = 0xA4,
	OPC_ACMPEQ          = 0xA5,
	OPC_ACMPNE          = 0xA6,
	OPC_GOTO            = 0xA7,
#if 0
	OPC_JSR             = 0xA8,
	OPC_RET             = 0xA9,
#endif
	OPC_TABLESWITCH     = 0xAA,
	OPC_LOOKUPSWITCH    = 0xAB,
	OPC_IRETURN         = 0xAC,
	OPC_LRETURN         = 0xAD,
	OPC_FRETURN         = 0xAE,
	OPC_DRETURN         = 0xAF,
	OPC_ARETURN         = 0xB0,
	OPC_RETURN          = 0xB1,
	OPC_GETSTATIC       = 0xB2,
	OPC_PUTSTATIC       = 0xB3,
	OPC_GETFIELD        = 0xB4,
	OPC_PUTFIELD        = 0xB5,
	OPC_INVOKEVIRTUAL   = 0xB6,
	OPC_INVOKESPECIAL   = 0xB7,
	OPC_INVOKESTATIC    = 0xB8,
	OPC_INVOKEINTERFACE = 0xB9,
#if 0
	OPC_XXXUNUSEDXXX    = 0xBA,
#endif
	OPC_NEW             = 0xBB,
	OPC_NEWARRAY        = 0xBC,
	OPC_ANEWARRAY       = 0xBD,
	OPC_ARRAYLENGTH     = 0xBE,
	OPC_ATHROW          = 0xBF,
	OPC_CHECKCAST       = 0xC0,
	OPC_INSTANCEOF      = 0xC1,
	OPC_MONITORENTER    = 0xC2,
	OPC_MONITOREXIT     = 0xC3,
	OPC_WIDE            = 0xC4,
	OPC_MULTIANEWARRAY  = 0xC5,
	OPC_IFNULL          = 0xC6,
	OPC_IFNONNULL       = 0xC7,
	OPC_GOTO_W          = 0xC8,
#if 0
	OPC_JSR_W           = 0xC9,
	OPC_BREAKPOINT      = 0xCA,
	OPC_IMPDEP1         = 0xFE,
	OPC_IMPDEP2         = 0xFF,
#endif
} opcode_kind_t;

#endif
